AC/AC1/ARQ1-GUIA09/02/Guia_0902.v
//Guia_0902.v

// ---------------------------
// -- Clock generator
// ---------------------------
module clock (output reg clk);
    initial
    begin
        clk = 1'b0;          // Inicializa o clock em nível baixo
    end
    always
    begin
        #12 clk = ~clk;      // Alterna o estado do clock a cada 12 unidades de tempo
    end
endmodule // clock


// ---------------------------
// -- Pulse generators with different periods
// ---------------------------
//`include "clock.v"

module pulse1 (output reg signal, input clock);
    always @(posedge clock)
    begin
        signal = 1'b1;       // Pulso em nível alto
        #4 signal = 1'b0;    // Alterna entre 1 e 0 em períodos de 4 unidades
        #4 signal = 1'b1;
        #4 signal = 1'b0;
        #4 signal = 1'b1;
        #4 signal = 1'b0;
    end
endmodule // pulse1

module pulse2 (output reg signal, input clock);
    always @(posedge clock)
    begin
        signal = 1'b1;       // Pulso com duração de 5 unidades em nível alto
        #5 signal = 1'b0;
    end
endmodule // pulse2

module pulse3 (output reg signal, input clock);
    always @(negedge clock)
    begin
        signal = 1'b1;       // Pulso alternando com período de 15 unidades
        #15 signal = 1'b0;
        #15 signal = 1'b1;
    end
endmodule // pulse3

module pulse4 (output reg signal, input clock);
    always @(negedge clock)
    begin
        signal = 1'b1;       // Pulso alternando com períodos de 20 unidades
        #20 signal = 1'b0;
        #20 signal = 1'b1;
        #20 signal = 1'b0;
    end
endmodule // pulse4

module Guia_0902;
    wire clock;               // Sinal de clock gerado
    clock CLK (clock);        // Instância do módulo clock

    wire p1, p2, p3, p4;      // Sinais gerados pelos módulos de pulso
    pulse1 PLS1 (p1, clock);  // Instância de pulse1
    pulse2 PLS2 (p2, clock);  // Instância de pulse2
    pulse3 PLS3 (p3, clock);  // Instância de pulse3
    pulse4 PLS4 (p4, clock);  // Instância de pulse4

    initial begin
        $dumpfile("Guia_0902.vcd"); // Arquivo de saída para simulação
        $dumpvars(1, clock, p1, p2, p3, p4); // Habilita sinais para captura
        #480 $finish;             // Finaliza a simulação após 480 unidades de tempo
    end
endmodule // Guia_0902


//iverilog -o Guia_0902 Guia_0902.v 
//vvp Guia_0902
//gtkwave Guia_0902.vcd

AC/AC1/ARQ1-GUIA09/02/Guia_0902.vcd
$date
	Tue Nov 26 19:40:38 2024
$end
$version
	Icarus Verilog
$end
$timescale
	1s
$end
$scope module Guia_0902 $end
$var wire 1 ! clock $end
$upscope $end
$scope module Guia_0902 $end
$var wire 1 " p1 $end
$upscope $end
$scope module Guia_0902 $end
$var wire 1 # p2 $end
$upscope $end
$scope module Guia_0902 $end
$var wire 1 $ p3 $end
$upscope $end
$scope module Guia_0902 $end
$var wire 1 % p4 $end
$upscope $end
$enddefinitions $end
$comment Show the parameter values. $end
$dumpall
$end
#0
$dumpvars
x%
x$
x#
x"
0!
$end
#12
1"
1#
1!
#16
0"
#17
0#
#20
1"
#24
1$
1%
0"
0!
#28
1"
#32
0"
#36
1#
1"
1!
#39
0$
#40
0"
#41
0#
#44
1"
0%
#48
0"
0!
#52
1"
#54
1$
#56
0"
#60
1#
1"
1!
#64
0"
1%
#65
0#
#68
1"
#72
0"
0!
#76
1"
#80
0"
#84
1#
1"
1!
0%
#87
0$
#88
0"
#89
0#
#92
1"
#96
1%
0"
0!
#100
1"
#102
1$
#104
0"
#108
1#
1"
1!
#112
0"
#113
0#
#116
1"
0%
#120
0"
0!
#124
1"
#128
0"
#132
1#
1"
1!
#135
0$
#136
0"
1%
#137
0#
#140
1"
#144
0"
0!
#148
1"
#150
1$
#152
0"
#156
1#
1"
1!
0%
#160
0"
#161
0#
#164
1"
#168
1%
0"
0!
#172
1"
#176
0"
#180
1#
1"
1!
#183
0$
#184
0"
#185
0#
#188
1"
0%
#192
0"
0!
#196
1"
#198
1$
#200
0"
#204
1#
1"
1!
#208
0"
1%
#209
0#
#212
1"
#216
0"
0!
#220
1"
#224
0"
#228
1#
1"
1!
0%
#231
0$
#232
0"
#233
0#
#236
1"
#240
1%
0"
0!
#244
1"
#246
1$
#248
0"
#252
1#
1"
1!
#256
0"
#257
0#
#260
1"
0%
#264
0"
0!
#268
1"
#272
0"
#276
1#
1"
1!
#279
0$
#280
0"
1%
#281
0#
#284
1"
#288
0"
0!
#292
1"
#294
1$
#296
0"
#300
1#
1"
1!
0%
#304
0"
#305
0#
#308
1"
#312
1%
0"
0!
#316
1"
#320
0"
#324
1#
1"
1!
#327
0$
#328
0"
#329
0#
#332
1"
0%
#336
0"
0!
#340
1"
#342
1$
#344
0"
#348
1#
1"
1!
#352
0"
1%
#353
0#
#356
1"
#360
0"
0!
#364
1"
#368
0"
#372
1#
1"
1!
0%
#375
0$
#376
0"
#377
0#
#380
1"
#384
1%
0"
0!
#388
1"
#390
1$
#392
0"
#396
1#
1"
1!
#400
0"
#401
0#
#404
1"
0%
#408
0"
0!
#412
1"
#416
0"
#420
1#
1"
1!
#423
0$
#424
0"
1%
#425
0#
#428
1"
#432
0"
0!
#436
1"
#438
1$
#440
0"
#444
1#
1"
1!
0%
#448
0"
#449
0#
#452
1"
#456
1%
0"
0!
#460
1"
#464
0"
#468
1#
1"
1!
#471
0$
#472
0"
#473
0#
#476
1"
0%
#480
0"
0!
