AC/AC1/ARQ1-GUIA09/01/Guia_0901.v
//Guia_0901.v

// ---------------------------
// -- test clock generator (2)
// ---------------------------

module clock (output clk);
    reg clk;
    initial
    begin
        clk = 1'b0;         // Inicializa o clock em nível lógico baixo
    end
    always
    begin
        #12 clk = ~clk;     // Inverte o estado do clock a cada 12 unidades de tempo
    end
endmodule // clock

module pulse (output signal, input clock);
    reg signal;
    always @(clock)
    begin
        signal = 1'b1;      // Pulso em nível alto
        #3 signal = 1'b0;   // Pulso em nível baixo após 3 unidades de tempo
        #3 signal = 1'b1;   // Pulso em nível alto novamente
        #3 signal = 1'b0;   // Finaliza o pulso após 3 unidades de tempo
    end
endmodule // pulse

module trigger (output signal, input on, input clock);
    reg signal;
    always @(posedge clock & on) // Gera gatilho apenas se 'on' estiver ativo
    begin
        #60 signal = 1'b1;   // Ativa o gatilho após 60 unidades de tempo
        #60 signal = 1'b0;   // Desativa o gatilho após mais 60 unidades de tempo
    end
endmodule // trigger

module Guia_0901;
    wire clk;                  // Sinal de clock gerado pelo módulo clock
    wire p_signal;             // Sinal gerado pelo módulo pulse
    wire t_signal;             // Sinal gerado pelo módulo trigger
    reg t_on;                  // Controle para ativar o gatilho

    // Instâncias dos módulos
    clock CLK1 (clk);          // Gera o clock
    pulse PULSE1 (p_signal, clk); // Gera os pulsos
    trigger TRIGGER1 (t_signal, t_on, clk); // Gera os gatilhos

    initial begin
        // Configurações para simulação
        $dumpfile("Guia_0901.vcd"); // Arquivo de saída para o GTKWave
        $dumpvars;

        // Simulação do gatilho
        t_on = 1'b0;           // Inicialmente, o gatilho está desativado
        #30 t_on = 1'b1;       // Ativa o gatilho após 30 unidades de tempo
        #120 t_on = 1'b0;      // Desativa o gatilho após 120 unidades de tempo
        #180 $finish;          // Finaliza a simulação
    end
endmodule // Guia_0901

//iverilog -o Guia_0901 Guia_0901.v
//vvp Guia_0901
//gtkwave Guia_0901.vcd

AC/AC1/ARQ1-GUIA09/01/Guia_0901.vcd
$date
	Tue Nov 26 19:30:12 2024
$end
$version
	Icarus Verilog
$end
$timescale
	1s
$end
$scope module Guia_0901 $end
$var wire 1 ! t_signal $end
$var wire 1 " p_signal $end
$var wire 1 # clk $end
$var reg 1 $ t_on $end
$scope module CLK1 $end
$var reg 1 # clk $end
$upscope $end
$scope module PULSE1 $end
$var wire 1 # clock $end
$var reg 1 " signal $end
$upscope $end
$scope module TRIGGER1 $end
$var wire 1 # clock $end
$var wire 1 $ on $end
$var reg 1 ! signal $end
$upscope $end
$upscope $end
$enddefinitions $end
$comment Show the parameter values. $end
$dumpall
$end
#0
$dumpvars
0$
0#
1"
x!
$end
#3
0"
#6
1"
#9
0"
#12
1"
1#
#15
0"
#18
1"
#21
0"
#24
1"
0#
#27
0"
#30
1"
1$
#33
0"
#36
1"
1#
#39
0"
#42
1"
#45
0"
#48
1"
0#
#51
0"
#54
1"
#57
0"
#60
1"
1#
#63
0"
#66
1"
#69
0"
#72
1"
0#
#75
0"
#78
1"
#81
0"
#84
1"
1#
#87
0"
#90
1"
#93
0"
#96
1"
0#
1!
#99
0"
#102
1"
#105
0"
#108
1"
1#
#111
0"
#114
1"
#117
0"
#120
1"
0#
#123
0"
#126
1"
#129
0"
#132
1"
1#
#135
0"
#138
1"
#141
0"
#144
1"
0#
#147
0"
#150
1"
0$
#153
0"
#156
1"
1#
0!
#159
0"
#162
1"
#165
0"
#168
1"
0#
#171
0"
#174
1"
#177
0"
#180
1"
1#
#183
0"
#186
1"
#189
0"
#192
1"
0#
#195
0"
#198
1"
#201
0"
#204
1"
1#
#207
0"
#210
1"
#213
0"
#216
1"
0#
#219
0"
#222
1"
#225
0"
#228
1"
1#
#231
0"
#234
1"
#237
0"
#240
1"
0#
#243
0"
#246
1"
#249
0"
#252
1"
1#
#255
0"
#258
1"
#261
0"
#264
1"
0#
#267
0"
#270
1"
#273
0"
#276
1"
1#
#279
0"
#282
1"
#285
0"
#288
1"
0#
#291
0"
#294
1"
#297
0"
#300
1"
1#
#303
0"
#306
1"
#309
0"
#312
1"
0#
#315
0"
#318
1"
#321
0"
#324
1"
1#
#327
0"
#330
1"
