AC/AC1/ARQ1-GUIA09/05/Guia_0905.v
//Guia_0905.v

// ---------------------------
// -- Clock generator
// ---------------------------
module clock (output reg clk);
    initial
    begin
        clk = 1'b0;          // Inicializa o clock em nível baixo
    end
    always
    begin
        #12 clk = ~clk;      // Alterna o estado do clock a cada 12 unidades de tempo
    end
endmodule // clock

// ---------------------------
// -- Pulse generator with 4-time-unit mark
// ---------------------------

module pulse (output reg signal, input clock);
    initial begin
        signal = 1'b0; // Inicializa o sinal do pulso em 0
    end

    always @(posedge clock) begin
        signal = 1'b1; // Ativa o sinal na borda de subida
        #4 signal = 1'b0; // Desativa o sinal após 4 unidades de tempo
    end
endmodule // pulse

module Guia_0905;
    wire clock;               // Sinal de clock gerado pelo módulo clock
    wire pulse_signal;        // Sinal do gerador de pulso

    clock CLK (clock);        // Instância do módulo clock
    pulse PLS (pulse_signal, clock); // Instância do módulo pulse

    initial begin
        $dumpfile("Guia_0905.vcd"); // Arquivo de saída para o GTKWave
        $dumpvars(1, clock, pulse_signal); // Habilita os sinais para captura
        #240 $finish;            // Finaliza a simulação após 240 unidades de tempo
    end
endmodule // Guia_0905

//iverilog -o Guia_0905 Guia_0905.v 
//vvp Guia_0905
//gtkwave Guia_0905.vcd

AC/AC1/ARQ1-GUIA09/05/Guia_0905.vcd
$date
	Wed Nov 27 14:52:47 2024
$end
$version
	Icarus Verilog
$end
$timescale
	1s
$end
$scope module Guia_0905 $end
$var wire 1 ! clock $end
$upscope $end
$scope module Guia_0905 $end
$var wire 1 " pulse_signal $end
$upscope $end
$enddefinitions $end
$comment Show the parameter values. $end
$dumpall
$end
#0
$dumpvars
0"
0!
$end
#12
1"
1!
#16
0"
#24
0!
#36
1"
1!
#40
0"
#48
0!
#60
1"
1!
#64
0"
#72
0!
#84
1"
1!
#88
0"
#96
0!
#108
1"
1!
#112
0"
#120
0!
#132
1"
1!
#136
0"
#144
0!
#156
1"
1!
#160
0"
#168
0!
#180
1"
1!
#184
0"
#192
0!
#204
1"
1!
#208
0"
#216
0!
#228
1"
1!
#232
0"
